setup.py
pip_upgrade/__init__.py
pip_upgrade/outdated_list.py
pip_upgrade.egg-info/PKG-INFO
pip_upgrade.egg-info/SOURCES.txt
pip_upgrade.egg-info/dependency_links.txt
pip_upgrade.egg-info/entry_points.txt
pip_upgrade.egg-info/requires.txt
pip_upgrade.egg-info/top_level.txt
pip_upgrade/commands/__init__.py
pip_upgrade/commands/install.py
pip_upgrade/commands/list.py