Metadata-Version: 1.1
Name: pip-upgrade
Version: 0.0.6
Summary: Provides functionality for updating your outdated packages.
Home-page: https://github.com/alistair-broomhead/pip_upgrade
Author: pip-upgrade authors
Author-email: UNKNOWN
License: MIT
Keywords: pip
Platform: UNKNOWN
Classifier: Development Status :: 4 - Beta
Classifier: Intended Audience :: Developers
Classifier: License :: OSI Approved :: MIT License
Classifier: Programming Language :: Python :: 2.7
Classifier: Programming Language :: Python :: 3.4
